<?xml version="1.0" encoding="UTF-8"?>
<con:soapui-project id="61529426-84c7-474e-be21-a648e4c96fe5" created="3.61.0" activeEnvironment="Default environment" encryptionMode="Not encrypted" name="SOAPProject" projectVersion="" updated="3.61.0 2025-06-17T10:42:49Z" xmlns:con="http://eviware.com/soapui/config">
  <con:settings/>
  <con:interface xsi:type="con:RestService" id="aa94bb3e-e2be-45c0-ac20-311bf5eb5ddd" wadlVersion="http://wadl.dev.java.net/2009/02" name="https://api.github.com" type="rest" xmlns:xsi="http://www.w3.org/2001/XMLSchema-instance">
    <con:settings id="f7a2e18e-37e7-4a3f-8ffe-2684d25480e2"/>
    <con:definitionCache type="TEXT" rootPart=""/>
    <con:endpoints>
      <con:endpoint>https://api.github.com</con:endpoint>
    </con:endpoints>
    <con:resource name="Emails" path="/user/emails" id="632b8dd5-6e02-436b-893c-2e91d672626a">
      <con:settings/>
      <con:parameters/>
      <con:method name="Emails" id="7d3b14ab-52b9-4283-88bf-d3ba3d0740a2" method="GET">
        <con:settings/>
        <con:parameters/>
        <con:representation type="FAULT">
          <con:mediaType>application/json; charset=utf-8</con:mediaType>
          <con:status>404</con:status>
          <con:params/>
          <con:element xmlns:ema="https://api.github.com/user/emails">ema:Fault</con:element>
        </con:representation>
        <con:representation type="RESPONSE">
          <con:mediaType>application/json; charset=utf-8</con:mediaType>
          <con:status>200</con:status>
          <con:params/>
          <con:element>Response</con:element>
        </con:representation>
        <con:request name="Request 1" id="33e5dda9-d852-4c84-a5c1-d027e805adf3" mediaType="application/json">
          <con:settings/>
          <con:endpoint>https://api.github.com</con:endpoint>
          <con:parameters/>
        </con:request>
      </con:method>
    </con:resource>
    <con:resource name="Keys" path="/user/keys" id="e3ca8478-d814-47fb-83c7-b823620216ac">
      <con:settings/>
      <con:parameters/>
      <con:method name="Keys" id="7b1c82b6-8f52-46ea-ae98-b018db1279c8" method="POST">
        <con:settings/>
        <con:parameters/>
        <con:representation type="REQUEST">
          <con:mediaType>application/json</con:mediaType>
          <con:params/>
        </con:representation>
        <con:representation type="FAULT">
          <con:mediaType>application/json; charset=utf-8</con:mediaType>
          <con:status>400</con:status>
          <con:params/>
          <con:element xmlns:keys="https://api.github.com/user/keys">keys:Fault</con:element>
        </con:representation>
        <con:representation type="RESPONSE">
          <con:mediaType>application/json; charset=utf-8</con:mediaType>
          <con:status>201</con:status>
          <con:params/>
          <con:element xmlns:keys="https://api.github.com/user/keys">keys:Response</con:element>
        </con:representation>
        <con:request name="Request 1" id="2f2bb23b-af0f-4dac-82f8-a14cf09b3ecf" mediaType="application/json">
          <con:settings/>
          <con:endpoint>https://api.github.com</con:endpoint>
          <con:parameters/>
        </con:request>
      </con:method>
    </con:resource>
    <con:resource name="KeyId" path="/user/keys/{keyId}" id="898e9eda-3d4e-49c9-bd60-73e6591f393a">
      <con:settings/>
      <con:parameters>
        <con:parameter>
          <con:name>keyId</con:name>
          <con:style>TEMPLATE</con:style>
        </con:parameter>
      </con:parameters>
      <con:method name="KeyId" id="4b87ef47-87a2-4b93-8bee-ff30b4803bce" method="DELETE">
        <con:settings/>
        <con:parameters/>
        <con:representation type="RESPONSE">
          <con:mediaType xsi:nil="true"/>
          <con:status>204</con:status>
          <con:params/>
          <con:element>data</con:element>
        </con:representation>
        <con:representation type="REQUEST">
          <con:mediaType>application/json</con:mediaType>
          <con:params/>
        </con:representation>
        <con:request name="Request 1" id="b4ceabdf-64d7-488c-8989-844a6462733f" mediaType="application/json">
          <con:settings/>
          <con:endpoint>https://api.github.com</con:endpoint>
          <con:parameters/>
          <con:parameterOrder>
            <con:entry>keyId</con:entry>
          </con:parameterOrder>
        </con:request>
      </con:method>
    </con:resource>
  </con:interface>
  <con:testSuite id="51fbe563-8279-4c39-aa74-4984e736e071" name="Test Suite">
    <con:settings id="6ba7b451-6018-43a2-84ce-ed3f864f410a"/>
    <con:runType>SEQUENTIAL</con:runType>
    <con:testCase id="c41ceb84-cb81-4c1c-8b19-fe3a6893ca67" discardOkResults="false" failOnError="false" failTestCaseOnErrors="true" keepSession="false" name="Test Case" searchProperties="true" timeout="0">
      <con:settings>
        <con:setting id="IncludeOverview">true</con:setting>
        <con:setting id="IncludeResults">true</con:setting>
        <con:setting id="FlowLayout">false</con:setting>
        <con:setting id="ErrorDetails">true</con:setting>
        <con:setting id="IncludeCoverage">true</con:setting>
        <con:setting id="GeneratableJUnitReport@Style">Multiple Pages</con:setting>
        <con:setting id="GeneratableJUnitReport@Folder">C:\Users\AshaAnnaThomas\OneDrive - IBM\Documents\FST2025\FST_API</con:setting>
        <con:setting id="GeneratableJUnitReport@Modify">true</con:setting>
      </con:settings>
      <con:testStep type="restrequest" name="GetRequest" id="dd6f72f2-b222-469e-abb2-ced89e3e2900">
        <con:settings/>
        <con:config service="https://api.github.com" resourcePath="/user/emails" methodName="Emails" xsi:type="con:RestRequestStep" xmlns:xsi="http://www.w3.org/2001/XMLSchema-instance">
          <con:restRequest name="GetRequest" id="33e5dda9-d852-4c84-a5c1-d027e805adf3" mediaType="application/json">
            <con:settings>
              <con:setting id="com.eviware.soapui.impl.wsdl.WsdlRequest@request-headers">&lt;xml-fragment/></con:setting>
            </con:settings>
            <con:endpoint>https://api.github.com</con:endpoint>
            <con:request/>
            <con:originalUri>https://api.github.com/user/emails</con:originalUri>
            <con:assertion type="Valid HTTP Status Codes" id="c39c07bd-e19d-4b7d-a679-9d9569aa060a" name="Valid HTTP Status Codes">
              <con:settings/>
              <con:configuration>
                <codes>200</codes>
              </con:configuration>
            </con:assertion>
            <con:assertion type="JsonPath Match" id="f4b210a5-59da-460d-a54a-b6e61d3eeec1" name="JSONPath Match">
              <con:configuration>
                <path>$[0]['email']</path>
                <content>"Asha.Anna.Thomas@ibm.com"</content>
                <allowWildcards>false</allowWildcards>
                <ignoreNamspaceDifferences>false</ignoreNamspaceDifferences>
                <ignoreComments>false</ignoreComments>
              </con:configuration>
            </con:assertion>
            <con:assertion type="JsonPath Match" id="35435fff-1b67-4ee6-a42a-c65759e5c74f" name="JSONPath Match 2">
              <con:configuration>
                <path>$[0]['visibility']</path>
                <content>"private"</content>
                <allowWildcards>false</allowWildcards>
                <ignoreNamspaceDifferences>false</ignoreNamspaceDifferences>
                <ignoreComments>false</ignoreComments>
              </con:configuration>
            </con:assertion>
            <con:credentials>
              <con:selectedAuthProfile>SoapProjectProfile</con:selectedAuthProfile>
              <con:authType>No Authorization</con:authType>
            </con:credentials>
            <con:jmsConfig JMSDeliveryMode="PERSISTENT"/>
            <con:parameters/>
          </con:restRequest>
        </con:config>
      </con:testStep>
      <con:testStep type="restrequest" name="PostRequest" id="1ac868b6-6294-4bd0-b626-eb3f842884b0">
        <con:settings/>
        <con:config service="https://api.github.com" resourcePath="/user/keys" methodName="Keys" xsi:type="con:RestRequestStep" xmlns:xsi="http://www.w3.org/2001/XMLSchema-instance">
          <con:restRequest name="PostRequest" id="2f2bb23b-af0f-4dac-82f8-a14cf09b3ecf" mediaType="application/json" postQueryString="false">
            <con:settings>
              <con:setting id="com.eviware.soapui.impl.wsdl.WsdlRequest@request-headers">&lt;xml-fragment/></con:setting>
            </con:settings>
            <con:endpoint>https://api.github.com</con:endpoint>
            <con:request>{
	"title": "TestKey",
	"key": "ssh-ed25519 AAAAC3NzaC1lZDI1NTE5AAAAIN/6fvrwwOcKGRoqeM4TkFZ41kiJSGFVrErTO76tNFPG"
}
</con:request>
            <con:originalUri>https://api.github.com/user/keys</con:originalUri>
            <con:assertion type="Valid HTTP Status Codes" id="5d2378dd-082d-43be-9904-32e34dddfb8b" name="Valid HTTP Status Codes">
              <con:settings/>
              <con:configuration>
                <codes>201</codes>
              </con:configuration>
            </con:assertion>
            <con:credentials>
              <con:selectedAuthProfile>SoapProjectProfile</con:selectedAuthProfile>
              <con:authType>No Authorization</con:authType>
            </con:credentials>
            <con:jmsConfig JMSDeliveryMode="PERSISTENT"/>
            <con:parameters/>
          </con:restRequest>
        </con:config>
      </con:testStep>
      <con:testStep type="transfer" name="Property Transfer" id="24571670-3744-465b-bac0-9cd5cfc19a4c">
        <con:settings/>
        <con:config xsi:type="con:PropertyTransfersStep" xmlns:xsi="http://www.w3.org/2001/XMLSchema-instance">
          <con:transfers setNullOnMissingSource="true" transferTextContent="true" failOnError="false" ignoreEmpty="false" transferToAll="false" entitize="false" transferChildNodes="false">
            <con:name>IdTransfer</con:name>
            <con:sourceType>Response</con:sourceType>
            <con:sourceStep>PostRequest</con:sourceStep>
            <con:sourcePath>$['id']</con:sourcePath>
            <con:targetType>keyId</con:targetType>
            <con:targetStep>DeleteRequest</con:targetStep>
            <con:targetPath/>
            <con:type>JSONPATH</con:type>
            <con:targetTransferType>JSONPATH</con:targetTransferType>
            <con:upgraded>true</con:upgraded>
          </con:transfers>
        </con:config>
      </con:testStep>
      <con:testStep type="restrequest" name="DeleteRequest" id="95b8429d-6ef3-456c-b0c5-2cfa850e284e">
        <con:settings/>
        <con:config service="https://api.github.com" resourcePath="/user/keys/{keyId}" methodName="KeyId" xsi:type="con:RestRequestStep" xmlns:xsi="http://www.w3.org/2001/XMLSchema-instance">
          <con:restRequest name="DeleteRequest" id="b4ceabdf-64d7-488c-8989-844a6462733f" mediaType="application/json" postQueryString="false">
            <con:settings>
              <con:setting id="com.eviware.soapui.impl.wsdl.WsdlRequest@request-headers">&lt;xml-fragment/></con:setting>
            </con:settings>
            <con:endpoint>https://api.github.com</con:endpoint>
            <con:request/>
            <con:originalUri>https://api.github.com/user/keys/129765439</con:originalUri>
            <con:assertion type="Valid HTTP Status Codes" id="0f93a594-f15d-4462-bb86-d7e3c2e805b1" name="Valid HTTP Status Codes">
              <con:settings/>
              <con:configuration>
                <codes>204</codes>
              </con:configuration>
            </con:assertion>
            <con:credentials>
              <con:selectedAuthProfile>SoapProjectProfile</con:selectedAuthProfile>
              <con:authType>No Authorization</con:authType>
            </con:credentials>
            <con:jmsConfig JMSDeliveryMode="PERSISTENT"/>
            <con:parameters>
              <con:entry key="keyId" value="129765940"/>
            </con:parameters>
            <con:parameterOrder>
              <con:entry>keyId</con:entry>
            </con:parameterOrder>
          </con:restRequest>
        </con:config>
      </con:testStep>
      <con:properties/>
      <con:reportParameters/>
    </con:testCase>
    <con:properties/>
    <con:reportParameters/>
  </con:testSuite>
  <con:requirements/>
  <con:properties/>
  <con:wssContainer/>
  <con:databaseConnectionContainer/>
  <con:jmsConnectionContainer/>
  <con:oAuth2ProfileContainer>
    <con:oAuth2Profile>
      <con:name>SoapProjectProfile</con:name>
      <con:type>OAuth 2.0</con:type>
      <con:accessToken/>
      <con:accessTokenPosition>HEADER</con:accessTokenPosition>
      <con:accessTokenStatus>ENTERED_MANUALLY</con:accessTokenStatus>
      <con:accessTokenStartingStatus>ENTERED_MANUALLY</con:accessTokenStartingStatus>
      <con:oAuth2Flow>AUTHORIZATION_CODE_GRANT</con:oAuth2Flow>
      <con:refreshAccessTokenMethod>AUTOMATIC</con:refreshAccessTokenMethod>
      <con:jwtConfiguration/>
      <con:responseType>id_token</con:responseType>
    </con:oAuth2Profile>
  </con:oAuth2ProfileContainer>
  <con:oAuth1ProfileContainer/>
  <con:reporting>
    <con:xmlTemplates/>
    <con:parameters/>
  </con:reporting>
  <con:eventHandlers type="RequestFilter.filterRequest" name="RequestFilter.filterRequest">
    <con:script>// Sample event script to add custom HTTP header to all outgoing REST, SOAP and HTTP(S) calls
// This code is often used for adding custom authentication to ReadyAPI functional tests

// If hardcoding the token, uncomment and change line 5
// token = '4567'

// If your token is parameterized in Project level custom property, uncomment line 8
// token = request.parent.testCase.testSuite.project.getProperty('auth_token').getValue()

// To modify all outgoing calls, remove comments from lines 11 to 16
// headers = request.requestHeaders
// if (headers.containsKey('auth_token2') == false) {
//   headers.put('auth_token2', token)
//   request.requestHeaders = headers
// }</con:script>
  </con:eventHandlers>
  <con:eventHandlers type="TestRunListener.afterStep" name="TestRunListener.afterStep">
    <con:script>// Save all test step results into files
// Change the directory path in line 5 to a location where you want to store details
// then uncomment lines 5 to 10

// filePath = 'C:\\tempOutputDirectory\\'
// fos = new java.io.FileOutputStream(filePath + testStepResult.testStep.label + '.txt', true)
// pw = new java.io.PrintWriter(fos)
// testStepResult.writeTo(pw)
// pw.close()
// fos.close()</con:script>
  </con:eventHandlers>
  <con:authRepository>
    <con:oAuth20AuthEntry>
      <con:name>SoapProjectProfile</con:name>
      <con:type>OAuth 2.0</con:type>
      <con:accessToken/>
      <con:accessTokenPosition>HEADER</con:accessTokenPosition>
      <con:accessTokenStatus>ENTERED_MANUALLY</con:accessTokenStatus>
      <con:accessTokenStartingStatus>ENTERED_MANUALLY</con:accessTokenStartingStatus>
      <con:oAuth2Flow>AUTHORIZATION_CODE_GRANT</con:oAuth2Flow>
      <con:refreshAccessTokenMethod>AUTOMATIC</con:refreshAccessTokenMethod>
      <con:jwtConfiguration/>
      <con:responseType>id_token</con:responseType>
    </con:oAuth20AuthEntry>
  </con:authRepository>
  <con:tags/>
</con:soapui-project>
